flexmock/__init__.py
flexmock/_api.py
flexmock/_integrations.py
flexmock/_pytest_plugin.py
flexmock/exceptions.py
flexmock/py.typed
flexmock-0.12.2.dist-info/LICENSE
flexmock-0.12.2.dist-info/METADATA
flexmock-0.12.2.dist-info/WHEEL
flexmock-0.12.2.dist-info/entry_points.txt
flexmock-0.12.2.dist-info/RECORD
