Metadata-Version: 2.1
Name: flexmock
Version: 0.12.2
Summary: flexmock is a testing library for Python that makes it easy to create mocks, stubs and fakes.
Home-page: https://github.com/flexmock/flexmock
License: BSD-2-Clause
Keywords: mock,testing,test,unittest,pytest
Author: Slavek Kabrda
Maintainer: Adarsh Krishnan
Maintainer-email: adarshk7@gmail.com
Requires-Python: >=3.8.0,<4.0.0
Classifier: Development Status :: 5 - Production/Stable
Classifier: Intended Audience :: Developers
Classifier: License :: OSI Approved :: BSD License
Classifier: Programming Language :: Python :: 3
Classifier: Programming Language :: Python :: 3.8
Classifier: Programming Language :: Python :: 3.9
Classifier: Programming Language :: Python :: 3.10
Classifier: Programming Language :: Python :: 3.11
Classifier: Programming Language :: Python :: 3.12
Classifier: Programming Language :: Python :: 3.13
Classifier: Programming Language :: Python :: 3 :: Only
Classifier: Programming Language :: Python :: Implementation :: PyPy
Classifier: Topic :: Software Development :: Testing
Classifier: Topic :: Software Development :: Testing :: Mocking
Classifier: Topic :: Software Development :: Testing :: Unit
Classifier: Typing :: Typed
Project-URL: Changes, https://flexmock.readthedocs.io/en/latest/changelog/
Project-URL: Documentation, https://flexmock.readthedocs.io
Project-URL: Issue Tracker, https://github.com/flexmock/flexmock/issues
Project-URL: Repository, https://github.com/flexmock/flexmock
Project-URL: Source Code, https://github.com/flexmock/flexmock
